odoo/addons/purchase_propagate_qty/README.rst
odoo/addons/purchase_propagate_qty/__init__.py
odoo/addons/purchase_propagate_qty/__manifest__.py
odoo/addons/purchase_propagate_qty/i18n/purchase_propagate_qty.pot
odoo/addons/purchase_propagate_qty/models/__init__.py
odoo/addons/purchase_propagate_qty/models/purchase.py
odoo/addons/purchase_propagate_qty/models/stock_move.py
odoo/addons/purchase_propagate_qty/readme/CONTRIBUTORS.rst
odoo/addons/purchase_propagate_qty/readme/DESCRIPTION.rst
odoo/addons/purchase_propagate_qty/readme/HISTORY.rst
odoo/addons/purchase_propagate_qty/readme/USAGE.rst
odoo/addons/purchase_propagate_qty/static/description/icon.png
odoo/addons/purchase_propagate_qty/static/description/index.html
odoo/addons/purchase_propagate_qty/tests/__init__.py
odoo/addons/purchase_propagate_qty/tests/test_purchase_delivery.py
odoo13_addon_purchase_propagate_qty-13.0.1.1.3.dist-info/METADATA
odoo13_addon_purchase_propagate_qty-13.0.1.1.3.dist-info/WHEEL
odoo13_addon_purchase_propagate_qty-13.0.1.1.3.dist-info/top_level.txt
odoo13_addon_purchase_propagate_qty-13.0.1.1.3.dist-info/RECORD
