Metadata-Version: 2.1
Name: odoo13-addon-purchase-propagate-qty
Version: 13.0.1.1.3
Summary: Quantity decrease on purchase line are propagated to the corresponding stock.move
Home-page: https://github.com/OCA/purchase-workflow
Author: Numerigraphe, Eficient, Camptocamp, Odoo Community Association (OCA)
Author-email: support@odoo-community.org
License: AGPL-3
Platform: UNKNOWN
Classifier: Programming Language :: Python
Classifier: Framework :: Odoo
Classifier: Framework :: Odoo :: 13.0
Classifier: License :: OSI Approved :: GNU Affero General Public License v3
Requires-Python: >=3.5
Requires-Dist: odoo (<13.1dev,>=13.0a)
